axonometry/__init__.py
axonometry/axo_config.toml
axonometry/axonometry.py
axonometry/config.py
axonometry/drawing.py
axonometry/line.py
axonometry/plane.py
axonometry/point.py
axonometry/surface.py
axonometry/trihedron.py
axonometry-0.1.4b9.dist-info/METADATA
axonometry-0.1.4b9.dist-info/WHEEL
axonometry-0.1.4b9.dist-info/top_level.txt
axonometry-0.1.4b9.dist-info/RECORD
