Metadata-Version: 2.4
Name: axonometry
Version: 0.1.4b9
Summary: Scripting library for generating axonometric drawings.
Author: Julien Rippinger
Project-URL: documentation, https://axonometry.readthedocs.io/en/latest/
Project-URL: repository, https://codeberg.org/mononym/axonometry/
Keywords: architecture,research,drawing,axonometry,projection
Classifier: Development Status :: 4 - Beta
Classifier: Intended Audience :: Education
Classifier: Intended Audience :: Science/Research
Classifier: License :: OSI Approved :: GNU General Public License v3 or later (GPLv3+)
Classifier: Natural Language :: English
Classifier: Programming Language :: Python
Classifier: Programming Language :: Python :: 3.12
Classifier: Programming Language :: Python :: 3.11
Classifier: Programming Language :: Python :: 3.10
Classifier: Topic :: Artistic Software
Classifier: Topic :: Education
Classifier: Topic :: Multimedia :: Graphics :: Editors :: Vector-Based
Classifier: Topic :: Scientific/Engineering :: Visualization
Requires-Python: <3.13,>=3.10
Requires-Dist: compas~=2.10
Requires-Dist: vpype[all]~=1.14
Requires-Dist: setuptools
Requires-Dist: CairoSVG
